meetup/__init__.py
meetup/client/__init__.py
meetup/client/client.py
meetup/client/errors.py
meetup_client-0.3.1.dist-info/LICENSE
meetup_client-0.3.1.dist-info/WHEEL
meetup_client-0.3.1.dist-info/METADATA
meetup_client-0.3.1.dist-info/RECORD
